etimedecorator/CHANGELOG.md
etimedecorator/README.md
etimedecorator/__init__.py
etimedecorator/etimedecorator.py
etimedecorator/test_etimedecorator.py
etimedecorator-1.0.1.dist-info/LICENSE
etimedecorator-1.0.1.dist-info/METADATA
etimedecorator-1.0.1.dist-info/WHEEL
etimedecorator-1.0.1.dist-info/top_level.txt
etimedecorator-1.0.1.dist-info/RECORD
